{
  "metadata": {
    "repository": "/home/user/go/src/github.com/opd-ai/murmur",
    "generated_at": "2026-05-06T08:40:21.575637156-04:00",
    "analysis_time": 4061835685,
    "files_processed": 332,
    "tool_version": "1.0.0",
    "go_version": ""
  },
  "overview": {
    "total_lines_of_code": 50251,
    "total_functions": 1428,
    "total_methods": 4726,
    "total_structs": 794,
    "total_interfaces": 40,
    "total_packages": 67,
    "total_files": 332
  },
  "functions": null,
  "structs": null,
  "interfaces": null,
  "packages": null,
  "circular_dependencies": null,
  "patterns": {
    "design_patterns": {
      "singleton": null,
      "factory": null,
      "builder": null,
      "observer": null,
      "strategy": null
    },
    "concurrency_patterns": {
      "worker_pools": null,
      "pipelines": null,
      "fan_out": null,
      "fan_in": null,
      "semaphores": null,
      "goroutines": {
        "total_count": 0,
        "anonymous_count": 0,
        "named_count": 0,
        "potential_leaks": null,
        "instances": null
      },
      "channels": {
        "total_count": 0,
        "buffered_count": 0,
        "unbuffered_count": 0,
        "directional_count": 0,
        "instances": null
      },
      "sync_primitives": {
        "mutexes": null,
        "rw_mutexes": null,
        "wait_groups": null,
        "once": null,
        "cond": null,
        "atomic": null
      }
    },
    "anti_patterns": {
      "god_objects": null,
      "long_methods": null,
      "deep_nesting": null,
      "magic_numbers": null,
      "performance_antipatterns": null
    }
  },
  "complexity": {
    "average_function_complexity": 0,
    "average_struct_complexity": 0,
    "highest_complexity": null,
    "complexity_distribution": null
  },
  "documentation": {
    "coverage": {
      "packages": 0,
      "functions": 0,
      "types": 0,
      "methods": 0,
      "overall": 0
    },
    "quality": {
      "average_length": 0,
      "code_examples": 0,
      "inline_comments": 0,
      "block_comments": 0,
      "quality_score": 0
    },
    "todo_comments": null,
    "fixme_comments": null,
    "hack_comments": null,
    "bug_comments": null,
    "xxx_comments": null,
    "deprecated_comments": null,
    "note_comments": null,
    "stale_annotations": 0,
    "annotations_by_category": null
  },
  "generics": {
    "type_parameters": {
      "count": 0,
      "constraints": null,
      "complexity": null
    },
    "instantiations": {
      "functions": null,
      "types": null,
      "methods": null
    },
    "constraint_usage": null,
    "complexity_score": 0
  },
  "duplication": {
    "clone_pairs": 44,
    "duplicated_lines": 602,
    "duplication_ratio": 0.005695418121268886,
    "largest_clone_size": 44,
    "clones": [
      {
        "hash": "2d85e2f0ac4d1d55",
        "type": "renamed",
        "instances": [
          {
            "file": "pkg/anonymous/mechanics/puzzles/puzzle_publisher.go",
            "start_line": 191,
            "end_line": 196,
            "node_count": 46
          },
          {
            "file": "pkg/anonymous/mechanics/sparks/spark_publisher.go",
            "start_line": 185,
            "end_line": 190,
            "node_count": 46
          }
        ],
        "line_count": 6,
        "severity": "warning",
        "suggestion": "Extract 6-line duplicate code block into a shared function. Found in 2 locations. Consider using generics or interface-based abstraction"
      },
      {
        "hash": "6717c1c3d5a27780",
        "type": "renamed",
        "instances": [
          {
            "file": "pkg/ui/device_pairing.go",
            "start_line": 191,
            "end_line": 196,
            "node_count": 34
          },
          {
            "file": "pkg/ui/puzzle_solver.go",
            "start_line": 114,
            "end_line": 119,
            "node_count": 34
          },
          {
            "file": "pkg/ui/puzzle_solver_stub.go",
            "start_line": 81,
            "end_line": 86,
            "node_count": 34
          }
        ],
        "line_count": 6,
        "severity": "warning",
        "suggestion": "Extract 6-line duplicate code block into a shared function. Found in 3 locations. Consider using generics or interface-based abstraction"
      },
      {
        "hash": "77bfaba501ace0fa",
        "type": "exact",
        "instances": [
          {
            "file": "pkg/ui/forge.go",
            "start_line": 70,
            "end_line": 75,
            "node_count": 34
          },
          {
            "file": "pkg/ui/forge_stub.go",
            "start_line": 56,
            "end_line": 61,
            "node_count": 34
          }
        ],
        "line_count": 6,
        "severity": "warning",
        "suggestion": "Extract 6-line duplicate code block into a shared function. Found in 2 locations"
      },
      {
        "hash": "8931731e396e72c3",
        "type": "renamed",
        "instances": [
          {
            "file": "pkg/anonymous/resonance/specter.go",
            "start_line": 423,
            "end_line": 428,
            "node_count": 36
          },
          {
            "file": "pkg/anonymous/resonance/specter.go",
            "start_line": 429,
            "end_line": 434,
            "node_count": 36
          },
          {
            "file": "pkg/anonymous/resonance/surface.go",
            "start_line": 403,
            "end_line": 408,
            "node_count": 36
          }
        ],
        "line_count": 6,
        "severity": "warning",
        "suggestion": "Extract 6-line duplicate code block into a shared function. Found in 3 locations. Consider using generics or interface-based abstraction"
      },
      {
        "hash": "cb86dbafaf142854",
        "type": "exact",
        "instances": [
          {
            "file": "pkg/ui/specter_detail.go",
            "start_line": 45,
            "end_line": 50,
            "node_count": 35
          },
          {
            "file": "pkg/ui/specter_detail_stub.go",
            "start_line": 29,
            "end_line": 34,
            "node_count": 35
          }
        ],
        "line_count": 6,
        "severity": "warning",
        "suggestion": "Extract 6-line duplicate code block into a shared function. Found in 2 locations"
      },
      {
        "hash": "25d47d1ae3075ca8",
        "type": "renamed",
        "instances": [
          {
            "file": "pkg/pulsemap/rendering/renderer.go",
            "start_line": 714,
            "end_line": 720,
            "node_count": 63
          },
          {
            "file": "pkg/ui/oracle_pool.go",
            "start_line": 347,
            "end_line": 353,
            "node_count": 63
          }
        ],
        "line_count": 7,
        "severity": "warning",
        "suggestion": "Extract 7-line duplicate code block into a shared function. Found in 2 locations. Consider using generics or interface-based abstraction"
      },
      {
        "hash": "2d3242c17ccc43b2",
        "type": "renamed",
        "instances": [
          {
            "file": "pkg/anonymous/resonance/specter.go",
            "start_line": 423,
            "end_line": 429,
            "node_count": 42
          },
          {
            "file": "pkg/anonymous/resonance/specter.go",
            "start_line": 430,
            "end_line": 436,
            "node_count": 42
          },
          {
            "file": "pkg/anonymous/resonance/surface.go",
            "start_line": 403,
            "end_line": 409,
            "node_count": 42
          }
        ],
        "line_count": 7,
        "severity": "warning",
        "suggestion": "Extract 7-line duplicate code block into a shared function. Found in 3 locations. Consider using generics or interface-based abstraction"
      },
      {
        "hash": "67f5f1d831b55402",
        "type": "renamed",
        "instances": [
          {
            "file": "pkg/store/masked_events.go",
            "start_line": 502,
            "end_line": 508,
            "node_count": 55
          },
          {
            "file": "pkg/store/masked_events.go",
            "start_line": 550,
            "end_line": 556,
            "node_count": 55
          }
        ],
        "line_count": 7,
        "severity": "warning",
        "suggestion": "Extract 7-line duplicate code block into a shared function. Found in 2 locations. Consider using generics or interface-based abstraction"
      },
      {
        "hash": "ec98940c0804be92",
        "type": "renamed",
        "instances": [
          {
            "file": "pkg/store/masked_events.go",
            "start_line": 498,
            "end_line": 504,
            "node_count": 62
          },
          {
            "file": "pkg/store/masked_events.go",
            "start_line": 548,
            "end_line": 554,
            "node_count": 62
          }
        ],
        "line_count": 7,
        "severity": "warning",
        "suggestion": "Extract 7-line duplicate code block into a shared function. Found in 2 locations. Consider using generics or interface-based abstraction"
      },
      {
        "hash": "fbfc06f74c6c3384",
        "type": "renamed",
        "instances": [
          {
            "file": "pkg/ui/compose.go",
            "start_line": 215,
            "end_line": 221,
            "node_count": 57
          },
          {
            "file": "pkg/ui/puzzle_solver.go",
            "start_line": 201,
            "end_line": 207,
            "node_count": 57
          }
        ],
        "line_count": 7,
        "severity": "warning",
        "suggestion": "Extract 7-line duplicate code block into a shared function. Found in 2 locations. Consider using generics or interface-based abstraction"
      },
      {
        "hash": "4c50b374a04cca9d",
        "type": "renamed",
        "instances": [
          {
            "file": "pkg/anonymous/resonance/specter.go",
            "start_line": 423,
            "end_line": 430,
            "node_count": 48
          },
          {
            "file": "pkg/anonymous/resonance/specter.go",
            "start_line": 431,
            "end_line": 438,
            "node_count": 48
          },
          {
            "file": "pkg/anonymous/resonance/surface.go",
            "start_line": 403,
            "end_line": 410,
            "node_count": 48
          }
        ],
        "line_count": 8,
        "severity": "warning",
        "suggestion": "Extract 8-line duplicate code block into a shared function. Found in 3 locations. Consider using generics or interface-based abstraction"
      },
      {
        "hash": "6a28791c0e673997",
        "type": "exact",
        "instances": [
          {
            "file": "pkg/pulsemap/rendering/effects/milestones.go",
            "start_line": 147,
            "end_line": 154,
            "node_count": 46
          },
          {
            "file": "pkg/pulsemap/rendering/effects/milestones_stub.go",
            "start_line": 121,
            "end_line": 128,
            "node_count": 46
          }
        ],
        "line_count": 8,
        "severity": "warning",
        "suggestion": "Extract 8-line duplicate code block into a shared function. Found in 2 locations"
      },
      {
        "hash": "73bfe8d3931bd068",
        "type": "renamed",
        "instances": [
          {
            "file": "pkg/ui/mark.go",
            "start_line": 436,
            "end_line": 443,
            "node_count": 57
          },
          {
            "file": "pkg/ui/specter_detail.go",
            "start_line": 321,
            "end_line": 330,
            "node_count": 57
          }
        ],
        "line_count": 8,
        "severity": "warning",
        "suggestion": "Extract 8-line duplicate code block into a shared function. Found in 2 locations. Consider using generics or interface-based abstraction"
      },
      {
        "hash": "ea1b0666b8706e25",
        "type": "renamed",
        "instances": [
          {
            "file": "pkg/onboarding/screens/recovery_screen.go",
            "start_line": 288,
            "end_line": 295,
            "node_count": 59
          },
          {
            "file": "pkg/onboarding/screens/recovery_screen.go",
            "start_line": 413,
            "end_line": 420,
            "node_count": 59
          }
        ],
        "line_count": 8,
        "severity": "warning",
        "suggestion": "Extract 8-line duplicate code block into a shared function. Found in 2 locations. Consider using generics or interface-based abstraction"
      },
      {
        "hash": "f52eb1a8c031fcea",
        "type": "renamed",
        "instances": [
          {
            "file": "pkg/anonymous/mechanics/councils/councils_publisher.go",
            "start_line": 222,
            "end_line": 229,
            "node_count": 66
          },
          {
            "file": "pkg/anonymous/mechanics/shadowplay/shadowplay_publisher.go",
            "start_line": 209,
            "end_line": 216,
            "node_count": 66
          }
        ],
        "line_count": 8,
        "severity": "warning",
        "suggestion": "Extract 8-line duplicate code block into a shared function. Found in 2 locations. Consider using generics or interface-based abstraction"
      },
      {
        "hash": "fe406ed6604dab48",
        "type": "renamed",
        "instances": [
          {
            "file": "pkg/anonymous/mechanics/hunts/hunt_publisher.go",
            "start_line": 237,
            "end_line": 244,
            "node_count": 75
          },
          {
            "file": "pkg/anonymous/mechanics/territory/territory_publisher.go",
            "start_line": 149,
            "end_line": 156,
            "node_count": 75
          }
        ],
        "line_count": 8,
        "severity": "warning",
        "suggestion": "Extract 8-line duplicate code block into a shared function. Found in 2 locations. Consider using generics or interface-based abstraction"
      },
      {
        "hash": "39747571e5b07e20",
        "type": "renamed",
        "instances": [
          {
            "file": "pkg/anonymous/resonance/specter.go",
            "start_line": 423,
            "end_line": 431,
            "node_count": 54
          },
          {
            "file": "pkg/anonymous/resonance/surface.go",
            "start_line": 403,
            "end_line": 411,
            "node_count": 54
          }
        ],
        "line_count": 9,
        "severity": "warning",
        "suggestion": "Extract 9-line duplicate code block into a shared function. Found in 2 locations. Consider using generics or interface-based abstraction"
      },
      {
        "hash": "4e12c061d34c0702",
        "type": "renamed",
        "instances": [
          {
            "file": "pkg/anonymous/mechanics/common.go",
            "start_line": 73,
            "end_line": 81,
            "node_count": 72
          },
          {
            "file": "pkg/content/waves/types.go",
            "start_line": 321,
            "end_line": 329,
            "node_count": 72
          }
        ],
        "line_count": 9,
        "severity": "warning",
        "suggestion": "Extract 9-line duplicate code block into a shared function. Found in 2 locations. Consider using generics or interface-based abstraction"
      },
      {
        "hash": "5fa0559b0684257f",
        "type": "renamed",
        "instances": [
          {
            "file": "pkg/ui/forge.go",
            "start_line": 276,
            "end_line": 284,
            "node_count": 52
          },
          {
            "file": "pkg/ui/masked_event.go",
            "start_line": 511,
            "end_line": 522,
            "node_count": 52
          }
        ],
        "line_count": 9,
        "severity": "warning",
        "suggestion": "Extract 9-line duplicate code block into a shared function. Found in 2 locations. Consider using generics or interface-based abstraction"
      },
      {
        "hash": "57b41c4affe47f43",
        "type": "renamed",
        "instances": [
          {
            "file": "pkg/ui/puzzle.go",
            "start_line": 149,
            "end_line": 158,
            "node_count": 37
          },
          {
            "file": "pkg/ui/territory_overview.go",
            "start_line": 134,
            "end_line": 143,
            "node_count": 37
          }
        ],
        "line_count": 10,
        "severity": "warning",
        "suggestion": "Extract 10-line duplicate code block into a shared function. Found in 2 locations. Consider using generics or interface-based abstraction"
      },
      {
        "hash": "5c0006d3ff2d3555",
        "type": "renamed",
        "instances": [
          {
            "file": "pkg/anonymous/mechanics/forge/forge_publisher.go",
            "start_line": 414,
            "end_line": 423,
            "node_count": 42
          },
          {
            "file": "pkg/anonymous/mechanics/shadowplay/shadowplay_publisher.go",
            "start_line": 454,
            "end_line": 463,
            "node_count": 42
          }
        ],
        "line_count": 10,
        "severity": "warning",
        "suggestion": "Extract 10-line duplicate code block into a shared function. Found in 2 locations. Consider using generics or interface-based abstraction"
      },
      {
        "hash": "7cfcdbac38551fa8",
        "type": "renamed",
        "instances": [
          {
            "file": "pkg/anonymous/mechanics/councils/councils_publisher.go",
            "start_line": 585,
            "end_line": 594,
            "node_count": 37
          },
          {
            "file": "pkg/anonymous/mechanics/hunts/hunt_publisher.go",
            "start_line": 321,
            "end_line": 330,
            "node_count": 37
          }
        ],
        "line_count": 10,
        "severity": "warning",
        "suggestion": "Extract 10-line duplicate code block into a shared function. Found in 2 locations. Consider using generics or interface-based abstraction"
      },
      {
        "hash": "b01a6d4f5252b245",
        "type": "renamed",
        "instances": [
          {
            "file": "pkg/ui/hunt_tracker.go",
            "start_line": 309,
            "end_line": 318,
            "node_count": 63
          },
          {
            "file": "pkg/ui/puzzle.go",
            "start_line": 383,
            "end_line": 397,
            "node_count": 63
          }
        ],
        "line_count": 10,
        "severity": "warning",
        "suggestion": "Extract 10-line duplicate code block into a shared function. Found in 2 locations. Consider using generics or interface-based abstraction"
      },
      {
        "hash": "cf96e9a6b8e0e8e0",
        "type": "renamed",
        "instances": [
          {
            "file": "pkg/ui/hunt_tracker.go",
            "start_line": 382,
            "end_line": 391,
            "node_count": 59
          },
          {
            "file": "pkg/ui/puzzle_solver.go",
            "start_line": 385,
            "end_line": 394,
            "node_count": 59
          }
        ],
        "line_count": 10,
        "severity": "warning",
        "suggestion": "Extract 10-line duplicate code block into a shared function. Found in 2 locations. Consider using generics or interface-based abstraction"
      },
      {
        "hash": "4d3297d36ccd14d2",
        "type": "exact",
        "instances": [
          {
            "file": "pkg/ui/puzzle_solver.go",
            "start_line": 114,
            "end_line": 124,
            "node_count": 59
          },
          {
            "file": "pkg/ui/puzzle_solver_stub.go",
            "start_line": 81,
            "end_line": 91,
            "node_count": 59
          }
        ],
        "line_count": 11,
        "severity": "warning",
        "suggestion": "Extract 11-line duplicate code block into a shared function. Found in 2 locations"
      },
      {
        "hash": "d12b59a9544a9666",
        "type": "exact",
        "instances": [
          {
            "file": "pkg/identity/recovery/reconstruct.go",
            "start_line": 137,
            "end_line": 147,
            "node_count": 94
          },
          {
            "file": "pkg/identity/recovery/reconstruct.go",
            "start_line": 158,
            "end_line": 168,
            "node_count": 94
          }
        ],
        "line_count": 11,
        "severity": "warning",
        "suggestion": "Extract 11-line duplicate code block into a shared function. Found in 2 locations"
      },
      {
        "hash": "5f6b16af5e012dad",
        "type": "renamed",
        "instances": [
          {
            "file": "pkg/identity/recovery/reconstruct.go",
            "start_line": 163,
            "end_line": 174,
            "node_count": 62
          },
          {
            "file": "pkg/identity/recovery/recovery.go",
            "start_line": 169,
            "end_line": 180,
            "node_count": 62
          }
        ],
        "line_count": 12,
        "severity": "warning",
        "suggestion": "Extract 12-line duplicate code block into a shared function. Found in 2 locations. Consider using generics or interface-based abstraction"
      },
      {
        "hash": "7dc80999288b7def",
        "type": "renamed",
        "instances": [
          {
            "file": "pkg/onboarding/screens/bootstrap_screen.go",
            "start_line": 392,
            "end_line": 403,
            "node_count": 59
          },
          {
            "file": "pkg/onboarding/screens/completion_screen.go",
            "start_line": 215,
            "end_line": 226,
            "node_count": 59
          }
        ],
        "line_count": 12,
        "severity": "warning",
        "suggestion": "Extract 12-line duplicate code block into a shared function. Found in 2 locations. Consider using generics or interface-based abstraction"
      },
      {
        "hash": "956e2ddb1c218a88",
        "type": "exact",
        "instances": [
          {
            "file": "pkg/ui/device_management.go",
            "start_line": 141,
            "end_line": 152,
            "node_count": 59
          },
          {
            "file": "pkg/ui/passphrase_prompt.go",
            "start_line": 147,
            "end_line": 158,
            "node_count": 59
          }
        ],
        "line_count": 12,
        "severity": "warning",
        "suggestion": "Extract 12-line duplicate code block into a shared function. Found in 2 locations"
      },
      {
        "hash": "92ec47c48e104f67",
        "type": "renamed",
        "instances": [
          {
            "file": "pkg/identity/ignition/ignition.go",
            "start_line": 307,
            "end_line": 320,
            "node_count": 45
          },
          {
            "file": "pkg/identity/ignition/ignition.go",
            "start_line": 322,
            "end_line": 335,
            "node_count": 45
          }
        ],
        "line_count": 14,
        "severity": "warning",
        "suggestion": "Extract 14-line duplicate code block into a shared function. Found in 2 locations. Consider using generics or interface-based abstraction"
      },
      {
        "hash": "e4b1300bd75ee6dc",
        "type": "exact",
        "instances": [
          {
            "file": "pkg/pulsemap/rendering/renderer.go",
            "start_line": 685,
            "end_line": 698,
            "node_count": 64
          },
          {
            "file": "pkg/pulsemap/rendering/renderer_stub.go",
            "start_line": 258,
            "end_line": 268,
            "node_count": 64
          }
        ],
        "line_count": 14,
        "severity": "warning",
        "suggestion": "Extract 14-line duplicate code block into a shared function. Found in 2 locations"
      },
      {
        "hash": "152168100ebe814f",
        "type": "exact",
        "instances": [
          {
            "file": "pkg/pulsemap/rendering/effects/cross_layer.go",
            "start_line": 159,
            "end_line": 173,
            "node_count": 64
          },
          {
            "file": "pkg/pulsemap/rendering/effects/cross_layer_stub.go",
            "start_line": 146,
            "end_line": 159,
            "node_count": 64
          }
        ],
        "line_count": 15,
        "severity": "warning",
        "suggestion": "Extract 15-line duplicate code block into a shared function. Found in 2 locations"
      },
      {
        "hash": "213e5dcb6a524d34",
        "type": "exact",
        "instances": [
          {
            "file": "pkg/pulsemap/rendering/renderer.go",
            "start_line": 603,
            "end_line": 618,
            "node_count": 61
          },
          {
            "file": "pkg/pulsemap/rendering/renderer_stub.go",
            "start_line": 207,
            "end_line": 218,
            "node_count": 61
          }
        ],
        "line_count": 16,
        "severity": "warning",
        "suggestion": "Extract 16-line duplicate code block into a shared function. Found in 2 locations"
      },
      {
        "hash": "442674399faba303",
        "type": "exact",
        "instances": [
          {
            "file": "pkg/pulsemap/rendering/effects/composite.go",
            "start_line": 49,
            "end_line": 65,
            "node_count": 72
          },
          {
            "file": "pkg/pulsemap/rendering/effects/composite_stub.go",
            "start_line": 34,
            "end_line": 46,
            "node_count": 72
          }
        ],
        "line_count": 17,
        "severity": "warning",
        "suggestion": "Extract 17-line duplicate code block into a shared function. Found in 2 locations"
      },
      {
        "hash": "c905f45123ef3396",
        "type": "renamed",
        "instances": [
          {
            "file": "pkg/content/propagation/bridge.go",
            "start_line": 341,
            "end_line": 357,
            "node_count": 57
          },
          {
            "file": "pkg/content/propagation/relay.go",
            "start_line": 168,
            "end_line": 184,
            "node_count": 57
          }
        ],
        "line_count": 17,
        "severity": "warning",
        "suggestion": "Extract 17-line duplicate code block into a shared function. Found in 2 locations. Consider using generics or interface-based abstraction"
      },
      {
        "hash": "7f144a5e658fdcb1",
        "type": "exact",
        "instances": [
          {
            "file": "pkg/identity/recovery/recovery.go",
            "start_line": 123,
            "end_line": 143,
            "node_count": 171
          },
          {
            "file": "pkg/identity/recovery/recovery.go",
            "start_line": 154,
            "end_line": 174,
            "node_count": 171
          }
        ],
        "line_count": 21,
        "severity": "violation",
        "suggestion": "Extract 21-line duplicate code block into a shared function. Found in 2 locations"
      },
      {
        "hash": "b8aff240fe0c64a2",
        "type": "exact",
        "instances": [
          {
            "file": "pkg/pulsemap/rendering/effects/gpu_particles.go",
            "start_line": 81,
            "end_line": 101,
            "node_count": 117
          },
          {
            "file": "pkg/pulsemap/rendering/effects/gpu_particles_stub.go",
            "start_line": 52,
            "end_line": 71,
            "node_count": 117
          }
        ],
        "line_count": 21,
        "severity": "violation",
        "suggestion": "Extract 21-line duplicate code block into a shared function. Found in 2 locations"
      },
      {
        "hash": "12e64b8855687ce9",
        "type": "exact",
        "instances": [
          {
            "file": "pkg/ui/gift.go",
            "start_line": 108,
            "end_line": 129,
            "node_count": 100
          },
          {
            "file": "pkg/ui/gift_stub.go",
            "start_line": 97,
            "end_line": 118,
            "node_count": 100
          }
        ],
        "line_count": 22,
        "severity": "violation",
        "suggestion": "Extract 22-line duplicate code block into a shared function. Found in 2 locations"
      },
      {
        "hash": "95cae0a1957ed44a",
        "type": "renamed",
        "instances": [
          {
            "file": "pkg/anonymous/mechanics/gifts/gifts_publisher.go",
            "start_line": 147,
            "end_line": 168,
            "node_count": 68
          },
          {
            "file": "pkg/anonymous/mechanics/marks/marks_publisher.go",
            "start_line": 147,
            "end_line": 168,
            "node_count": 68
          }
        ],
        "line_count": 22,
        "severity": "violation",
        "suggestion": "Extract 22-line duplicate code block into a shared function. Found in 2 locations. Consider using generics or interface-based abstraction"
      },
      {
        "hash": "5b879d8c0bb883de",
        "type": "exact",
        "instances": [
          {
            "file": "pkg/pulsemap/overlays/marks.go",
            "start_line": 56,
            "end_line": 78,
            "node_count": 103
          },
          {
            "file": "pkg/pulsemap/overlays/marks_stub.go",
            "start_line": 44,
            "end_line": 63,
            "node_count": 103
          }
        ],
        "line_count": 23,
        "severity": "violation",
        "suggestion": "Extract 23-line duplicate code block into a shared function. Found in 2 locations"
      },
      {
        "hash": "24abfc9d63d0b562",
        "type": "exact",
        "instances": [
          {
            "file": "pkg/pulsemap/overlays/marks.go",
            "start_line": 338,
            "end_line": 361,
            "node_count": 87
          },
          {
            "file": "pkg/pulsemap/overlays/marks_stub.go",
            "start_line": 177,
            "end_line": 200,
            "node_count": 87
          }
        ],
        "line_count": 24,
        "severity": "violation",
        "suggestion": "Extract 24-line duplicate code block into a shared function. Found in 2 locations"
      },
      {
        "hash": "deceba632d0c9536",
        "type": "renamed",
        "instances": [
          {
            "file": "pkg/ui/puzzle.go",
            "start_line": 368,
            "end_line": 392,
            "node_count": 111
          },
          {
            "file": "pkg/ui/puzzle_solver.go",
            "start_line": 316,
            "end_line": 333,
            "node_count": 111
          }
        ],
        "line_count": 25,
        "severity": "violation",
        "suggestion": "Extract 25-line duplicate code block into a shared function. Found in 2 locations. Consider using generics or interface-based abstraction"
      },
      {
        "hash": "12371ed94308de5f",
        "type": "exact",
        "instances": [
          {
            "file": "pkg/pulsemap/rendering/effects/cross_layer.go",
            "start_line": 60,
            "end_line": 91,
            "node_count": 122
          },
          {
            "file": "pkg/pulsemap/rendering/effects/cross_layer_stub.go",
            "start_line": 53,
            "end_line": 79,
            "node_count": 122
          }
        ],
        "line_count": 32,
        "severity": "violation",
        "suggestion": "Extract 32-line duplicate code block into a shared function. Found in 2 locations"
      },
      {
        "hash": "0392f561a543474c",
        "type": "exact",
        "instances": [
          {
            "file": "pkg/ui/mark.go",
            "start_line": 117,
            "end_line": 160,
            "node_count": 170
          },
          {
            "file": "pkg/ui/mark_stub.go",
            "start_line": 90,
            "end_line": 129,
            "node_count": 170
          }
        ],
        "line_count": 44,
        "severity": "violation",
        "suggestion": "Extract 44-line duplicate code block into a shared function. Found in 2 locations"
      }
    ]
  },
  "naming": {
    "file_name_violations": 0,
    "identifier_violations": 0,
    "package_name_violations": 0,
    "overall_naming_score": 0,
    "file_name_issues": null,
    "identifier_issues": null,
    "package_name_issues": null
  },
  "placement": {
    "misplaced_functions": 0,
    "misplaced_methods": 0,
    "low_cohesion_files": 0,
    "avg_file_cohesion": 0,
    "function_issues": null,
    "method_issues": null,
    "cohesion_issues": null
  },
  "organization": {
    "oversized_files": null,
    "oversized_packages": null,
    "deep_directories": null,
    "high_fan_in_packages": null,
    "high_fan_out_packages": null,
    "avg_package_instability": 0
  },
  "burden": {
    "magic_numbers": null,
    "dead_code": {
      "unreferenced_functions": null,
      "unreachable_code": null,
      "total_dead_lines": 0,
      "dead_code_percent": 0
    },
    "complex_signatures": null,
    "deeply_nested_functions": null,
    "feature_envy_methods": null
  },
  "scores": {
    "file_scores": null,
    "package_scores": null
  },
  "test_coverage": {
    "function_coverage_rate": 0,
    "complexity_coverage_rate": 0,
    "high_risk_functions": null,
    "coverage_gaps": null
  },
  "test_quality": {
    "total_tests": 0,
    "avg_assertions_per_test": 0,
    "test_files": null
  }
}
